{
  "groups": [
    {
      "name": "blog.security",
      "type": "john.blog.properties.BlogSecurityProperties",
      "sourceType": "john.blog.properties.BlogSecurityProperties"
    }
  ],
  "properties": [
    {
      "name": "blog.security.qq-properties",
      "type": "john.blog.properties.QQProperties",
      "sourceType": "john.blog.properties.BlogSecurityProperties"
    },
    {
      "name": "blog.security.we-chat-properties",
      "type": "john.blog.properties.WeChatProperties",
      "sourceType": "john.blog.properties.BlogSecurityProperties"
    }
  ],
  "hints": []
}